pkgsample/__init__.py
pkgsample/add.py
pkgsample/add_cli.py
pkgsample-0.1.1.dist-info/LICENSE.txt
pkgsample-0.1.1.dist-info/METADATA
pkgsample-0.1.1.dist-info/WHEEL
pkgsample-0.1.1.dist-info/entry_points.txt
pkgsample-0.1.1.dist-info/top_level.txt
pkgsample-0.1.1.dist-info/RECORD
