Metadata-Version: 2.1
Name: pkgsample
Version: 0.1.1
Summary: An example package demonstrating how to make one
Author-email: Ned Example <ned@example.com>
License: Apache-2.0
Project-URL: Source code, https://github.com/nedbat/pkgsample
Project-URL: Issue tracker, https://github.com/nedbat/pkgsample/issues
Classifier: Development Status :: 2 - Pre-Alpha
Classifier: License :: OSI Approved :: Apache Software License
Classifier: Programming Language :: Python
Classifier: Programming Language :: Python :: 3
Classifier: Programming Language :: Python :: 3.9
Classifier: Programming Language :: Python :: 3.10
Classifier: Programming Language :: Python :: 3.11
Requires-Python: >=3.9
License-File: LICENSE.txt
Requires-Dist: rich
